ruvrics/__init__.py
ruvrics/__main__.py
ruvrics/cli.py
ruvrics/comparison.py
ruvrics/config.py
ruvrics/analysis/__init__.py
ruvrics/analysis/fingerprint.py
ruvrics/analysis/recommender.py
ruvrics/analysis/scorer.py
ruvrics/core/__init__.py
ruvrics/core/adapters.py
ruvrics/core/executor.py
ruvrics/core/models.py
ruvrics/metrics/__init__.py
ruvrics/metrics/claims.py
ruvrics/metrics/length.py
ruvrics/metrics/semantic.py
ruvrics/metrics/structural.py
ruvrics/metrics/tool.py
ruvrics/output/__init__.py
ruvrics/output/formatter.py
ruvrics/output/markdown_report.py
ruvrics/utils/__init__.py
ruvrics/utils/errors.py
ruvrics/utils/telemetry.py
ruvrics-0.2.3.dist-info/licenses/LICENSE
ruvrics-0.2.3.dist-info/METADATA
ruvrics-0.2.3.dist-info/WHEEL
ruvrics-0.2.3.dist-info/entry_points.txt
ruvrics-0.2.3.dist-info/top_level.txt
ruvrics-0.2.3.dist-info/RECORD
