Metadata-Version: 2.4
Name: ruvrics
Version: 0.2.3
Summary: AI Behavioral Stability & Reliability Engine - Measure LLM consistency and reliability
Author: Ruvrics Team
License-Expression: Apache-2.0
Project-URL: Homepage, https://github.com/ruvrics-ai/ruvrics
Project-URL: Documentation, https://github.com/ruvrics-ai/ruvrics#readme
Project-URL: Repository, https://github.com/ruvrics-ai/ruvrics
Project-URL: Issues, https://github.com/ruvrics-ai/ruvrics/issues
Keywords: AI,LLM,stability,testing,reliability,openai,anthropic
Classifier: Development Status :: 3 - Alpha
Classifier: Intended Audience :: Developers
Classifier: Programming Language :: Python :: 3.10
Classifier: Programming Language :: Python :: 3.11
Classifier: Programming Language :: Python :: 3.12
Classifier: Topic :: Software Development :: Testing
Classifier: Topic :: Scientific/Engineering :: Artificial Intelligence
Requires-Python: >=3.10
License-File: LICENSE
Requires-Dist: click>=8.1.0
Requires-Dist: openai>=1.0.0
Requires-Dist: anthropic>=0.18.0
Requires-Dist: sentence-transformers>=2.2.0
Requires-Dist: numpy<2.0,>=1.24.0
Requires-Dist: rich>=13.0.0
Requires-Dist: pydantic>=2.0.0
Requires-Dist: python-dotenv>=1.0.0
Provides-Extra: dev
Requires-Dist: pytest>=7.0.0; extra == "dev"
Requires-Dist: pytest-cov>=4.0.0; extra == "dev"
Requires-Dist: pytest-mock>=3.12.0; extra == "dev"
Requires-Dist: black>=23.0.0; extra == "dev"
Requires-Dist: ruff>=0.1.0; extra == "dev"
Requires-Dist: mypy>=1.0.0; extra == "dev"
Dynamic: license-file
